tiktok_hashtag_analysis/__init__.py
tiktok_hashtag_analysis/base.py
tiktok_hashtag_analysis/cli.py
tiktok_hashtag_analysis/version.py
tiktok_hashtag_analysis-2.0.3.dist-info/LICENSE
tiktok_hashtag_analysis-2.0.3.dist-info/METADATA
tiktok_hashtag_analysis-2.0.3.dist-info/WHEEL
tiktok_hashtag_analysis-2.0.3.dist-info/entry_points.txt
tiktok_hashtag_analysis-2.0.3.dist-info/top_level.txt
tiktok_hashtag_analysis-2.0.3.dist-info/RECORD
