Metadata-Version: 2.1
Name: tiktok-hashtag-analysis
Version: 2.0.3
Summary: Analyze hashtags within posts scraped from TikTok
Home-page: https://github.com/bellingcat/tiktok-hashtag-analysis
Author: Bellingcat
Author-email: tech@bellingcat.com
License: MIT License
Classifier: Development Status :: 5 - Production/Stable
Classifier: Intended Audience :: Information Technology
Classifier: License :: OSI Approved :: MIT License
Classifier: Natural Language :: English
Classifier: Programming Language :: Python :: 3
License-File: LICENSE
Requires-Dist: seaborn
Requires-Dist: matplotlib
Requires-Dist: TikTokApi
Requires-Dist: requests
Requires-Dist: yt-dlp
Requires-Dist: tenacity
Requires-Dist: msvc-runtime ; os_name == "nt"
Provides-Extra: dev
Requires-Dist: pytest ; extra == 'dev'
Requires-Dist: pytest-cov ; extra == 'dev'
Requires-Dist: pytest-html ; extra == 'dev'
Requires-Dist: pytest-metadata ; extra == 'dev'
Requires-Dist: black ; extra == 'dev'
Requires-Dist: mypy ; extra == 'dev'
